psssodls/__init__.py
psssodls-0.3.data/scripts/psssodls
psssodls-0.3.dist-info/LICENSE
psssodls-0.3.dist-info/METADATA
psssodls-0.3.dist-info/WHEEL
psssodls-0.3.dist-info/top_level.txt
psssodls-0.3.dist-info/RECORD
