Metadata-Version: 2.1
Name: psssodls
Version: 0.3
Summary: Generate PSSSODLS in Minion 3 format.
Home-page: https://gitlab.com/MHenderson1/psssodls-generator
Author: Matthew Henderson
Author-email: matthew.james.henderson@gmail.com
License: MIT
Platform: UNKNOWN
Classifier: Programming Language :: Python :: 3
Classifier: License :: OSI Approved :: MIT License
Classifier: Operating System :: OS Independent
Requires-Python: >=3.6
